trujillo/__init__.py
trujillo/sunat/__init__.py
trujillo/sunat/token.py
trujillo/sunat/validate.py
trujillo_sunat_package-0.0.1.dist-info/LICENCE
trujillo_sunat_package-0.0.1.dist-info/METADATA
trujillo_sunat_package-0.0.1.dist-info/WHEEL
trujillo_sunat_package-0.0.1.dist-info/top_level.txt
trujillo_sunat_package-0.0.1.dist-info/RECORD
