Metadata-Version: 2.1
Name: trujillo-sunat-package
Version: 0.0.1
Summary: Este paquete está diseñado específicamente para proporcionar clases que permiten a los usuarios establecer una conexión eficiente con las API SUNAT
Author: Fernando Colque
Author-email: fernando.colque@terranovatrading.com.pe
License: MIT
License-File: LICENCE
Requires-Dist: pandas
Requires-Dist: requests
